<?xml version="1.0" encoding="utf-8" standalone="yes" ?>
<T3locallang>
	<meta type="array">
		<type>database</type>
		<description>Language labels for database tables/fields belonging to extension 'news2'</description>
	</meta>
	<data type="array">
		<languageKey index="default" type="array">
			<label index="tx_news2_domain_model_news.tabs.relations">Relations</label>
			<label index="tx_news2_domain_model_news">News</label>
			<label index="tx_news2_domain_model_news.teaser">Teaser</label>
			<label index="tx_news2_domain_model_news.datetime">Date &amp; Time</label>
			<label index="tx_news2_domain_model_news.archive">Archive</label>
			<label index="tx_news2_domain_model_news.categories">Categories</label>
			<label index="tx_news2_domain_model_news.related">Related News</label>
			<label index="tx_news2_domain_model_news.related_files">Related Files</label>
			<label index="tx_news2_domain_model_news.related_links">Related Links</label>
			<label index="tx_news2_domain_model_news.type.I.0">News</label>
			<label index="tx_news2_domain_model_news.type.I.1">Internal Page</label>
			<label index="tx_news2_domain_model_news.type.I.2">External Page</label>
			<label index="tx_news2_domain_model_news.media">Media Element</label>
			<label index="tx_news2_domain_model_news.istopnews">Top news</label>
			<label index="tx_news2_domain_model_news.content_elements">Content elements</label>
			<label index="tx_news2_domain_model_news.tags">Tags</label>
			<label index="tx_news2_domain_model_news.tags.add">Add a new tag</label>
			<label index="tx_news2_domain_model_news.tags.list">List all tags</label>

			<label index="tx_news2_domain_model_category">News Category</label>
			<label index="tx_news2_domain_model_category.title">Title</label>
			<label index="tx_news2_domain_model_category.description">Description</label>
			<label index="tx_news2_domain_model_category.image">Image</label>
			<label index="tx_news2_domain_model_category.parentcategory">Parent Category</label>
			<label index="tx_news2_domain_model_category.single_pid">Single-view page for news from this category</label>
			<label index="tx_news2_domain_model_category.shortcut">News category shortcut</label>

			<label index="tx_news2_domain_model_media">News Media Element</label>
			<label index="tx_news2_domain_model_media.caption">Caption</label>
			<label index="tx_news2_domain_model_media.media">Image</label>
			<label index="tx_news2_domain_model_media.type.I.0">Image</label>
			<label index="tx_news2_domain_model_media.type.I.1">Video &amp; Audio</label>
			<label index="tx_news2_domain_model_media.type.I.2">HTML</label>
			<label index="tx_news2_domain_model_media.type.I.3">DAM record</label>
			<label index="tx_news2_domain_model_media.html">HTML</label>
			<label index="tx_news2_domain_model_media.multimedia">Video- / Audio-URL</label>
			<label index="tx_news2_domain_model_media.dam">DAM record</label>
			<label index="tx_news2_domain_model_media.show">Show</label>
			<label index="tx_news2_domain_model_media.showinpreview">Show in preview views</label>

			<label index="tx_news2_domain_model_file">News File Element</label>
			<label index="tx_news2_domain_model_file.title">Title</label>
			<label index="tx_news2_domain_model_file.description">Description</label>
			<label index="tx_news2_domain_model_file.file">File</label>

			<label index="tx_news2_domain_model_link">News Link Element</label>
			<label index="tx_news2_domain_model_link.title">Title</label>
			<label index="tx_news2_domain_model_link.description">Description</label>
			<label index="tx_news2_domain_model_link.uri">URL</label>

			<label index="tx_news2_domain_model_tag">News Tag</label>
			<label index="tx_news2_domain_model_tag.title">Title</label>
		</languageKey>

		<languageKey index="es" type="array">
			<label index="tx_news2_domain_model_news.tabs.relations">Relaciones</label>
			<label index="tx_news2_domain_model_news">Noticias</label>
			<label index="tx_news2_domain_model_news.teaser">Resumen</label>
			<label index="tx_news2_domain_model_news.datetime">Fecha &amp; Hora</label>
			<label index="tx_news2_domain_model_news.archive">Archivo</label>
			<label index="tx_news2_domain_model_news.categories">Categorias</label>
			<label index="tx_news2_domain_model_news.related">Noticas relacionadas</label>
			<label index="tx_news2_domain_model_news.related_files">Ficheros relacionados</label>
			<label index="tx_news2_domain_model_news.related_links">Links relacionados</label>
			<label index="tx_news2_domain_model_news.type.I.0">Noticia</label>
			<label index="tx_news2_domain_model_news.type.I.1">Página interna</label>
			<label index="tx_news2_domain_model_news.type.I.2">Página externa</label>
			<label index="tx_news2_domain_model_news.media">Elemento multimedia</label>
			<label index="tx_news2_domain_model_news.istopnews">Noticias destacadas</label>
			<label index="tx_news2_domain_model_news.content_elements">Elementos de contenido</label>
			<label index="tx_news2_domain_model_news.tags">Tags</label>
			<label index="tx_news2_domain_model_news.tags.add">Add a new tag</label>
			<label index="tx_news2_domain_model_news.tags.list">List all tags</label>

			<label index="tx_news2_domain_model_category">Categoría de noticias</label>
			<label index="tx_news2_domain_model_category.title">Título</label>
			<label index="tx_news2_domain_model_category.description">Descripción</label>
			<label index="tx_news2_domain_model_category.image">Imágen</label>
			<label index="tx_news2_domain_model_category.parentcategory">Categoría padre</label>
			<label index="tx_news2_domain_model_category.single_pid">Página de vista individual para noticas de esta categoría</label>
			<label index="tx_news2_domain_model_category.shortcut">Atajo de categoría</label>

			<label index="tx_news2_domain_model_media">Elemento multimedia asociado a noticias</label>
			<label index="tx_news2_domain_model_media.caption">Titulo</label>
			<label index="tx_news2_domain_model_media.media">Imágen</label>
			<label index="tx_news2_domain_model_media.type.I.0">Imágen</label>
			<label index="tx_news2_domain_model_media.type.I.1">Video &amp; Audio</label>
			<label index="tx_news2_domain_model_media.type.I.2">HTML</label>
			<label index="tx_news2_domain_model_media.type.I.3">registro de DAM</label>
			<label index="tx_news2_domain_model_media.html">HTML</label>
			<label index="tx_news2_domain_model_media.multimedia">Video- / Audio-URL</label>
			<label index="tx_news2_domain_model_media.dam">registro de DAM</label>
			<label index="tx_news2_domain_model_media.show">Mostrar</label>
			<label index="tx_news2_domain_model_media.showinpreview">Mostrar en previsualización</label>

			<label index="tx_news2_domain_model_file">Fichero asociado a noticias</label>
			<label index="tx_news2_domain_model_file.title">Título</label>
			<label index="tx_news2_domain_model_file.description">Descripción</label>
			<label index="tx_news2_domain_model_file.file">Fichero</label>

			<label index="tx_news2_domain_model_link">Link asociado a noticas</label>
			<label index="tx_news2_domain_model_link.title">Título</label>
			<label index="tx_news2_domain_model_link.description">Descripción</label>
			<label index="tx_news2_domain_model_link.uri">URL</label>
		</languageKey>

		<languageKey index="de" type="array">
			<label index="tx_news2_domain_model_news.tabs.relations">Relationen</label>
			<label index="tx_news2_domain_model_news">News</label>
			<label index="tx_news2_domain_model_news.teaser">Teaser</label>
			<label index="tx_news2_domain_model_news.datetime">Datum</label>
			<label index="tx_news2_domain_model_news.archive">Archivdatum</label>
			<label index="tx_news2_domain_model_news.category">Kategorie</label>
			<label index="tx_news2_domain_model_news.related">Verwandte Artikel</label>
			<label index="tx_news2_domain_model_news.related_files">Verwandte Dateien</label>
			<label index="tx_news2_domain_model_news.related_links">Verwandte Links</label>
			<label index="tx_news2_domain_model_news.type.I.0">News</label>
			<label index="tx_news2_domain_model_news.type.I.1">Interne Seite</label>
			<label index="tx_news2_domain_model_news.type.I.2">Externe Seite/URL</label>
			<label index="tx_news2_domain_model_news.media">Medienelement</label>
			<label index="tx_news2_domain_model_news.istopnews">Top news</label>
			<label index="tx_news2_domain_model_news.content_elements">Content elements</label>
			<label index="tx_news2_domain_model_news.tags">Tags</label>
			<label index="tx_news2_domain_model_news.tags.add">Neuen Tag hinzufügen</label>
			<label index="tx_news2_domain_model_news.tags.list">Liste aller Tags</label>

			<label index="tx_news2_domain_model_category">News Kategorie</label>
			<label index="tx_news2_domain_model_category.title">Titel</label>
			<label index="tx_news2_domain_model_category.description">Beschreibung</label>
			<label index="tx_news2_domain_model_category.image">Bild</label>
			<label index="tx_news2_domain_model_category.parentcategory">Elternkategorie</label>
			<label index="tx_news2_domain_model_category.single_pid">Seite für Einzelansicht von News dieser Kategorie</label>
			<label index="tx_news2_domain_model_category.shortcut">Verknüpfte Seite</label>

			<label index="tx_news2_domain_model_media">News Medienelement</label>
			<label index="tx_news2_domain_model_media.caption">Caption</label>
			<label index="tx_news2_domain_model_media.media">Medientyp</label>
			<label index="tx_news2_domain_model_media.type.I.0">Bild</label>
			<label index="tx_news2_domain_model_media.type.I.2">HTML</label>
			<label index="tx_news2_domain_model_media.type.I.3">DAM</label>
			<label index="tx_news2_domain_model_media.html">HTML</label>
			<label index="tx_news2_domain_model_media.multimedia">Video URL</label>
			<label index="tx_news2_domain_model_media.show">Anzeigen</label>
			<label index="tx_news2_domain_model_media.showinpreview">In Voransicht anzeigen</label>

			<label index="tx_news2_domain_model_file">News Dateielement</label>
			<label index="tx_news2_domain_model_file.title">Titel</label>
			<label index="tx_news2_domain_model_file.description">Beschreibung</label>
			<label index="tx_news2_domain_model_file.file">Datei</label>

			<label index="tx_news2_domain_model_link">News Linkelement</label>
			<label index="tx_news2_domain_model_link.title">Titel</label>
			<label index="tx_news2_domain_model_link.description">Beschreibung</label>
			<label index="tx_news2_domain_model_link.uri">URL</label>
		</languageKey>
	</data>
</T3locallang>